abc_test_abc_sdk/__init__.py
abc_test_abc_sdk/api_client.py
abc_test_abc_sdk/api_response.py
abc_test_abc_sdk/configuration.py
abc_test_abc_sdk/exceptions.py
abc_test_abc_sdk/py.typed
abc_test_abc_sdk/rest.py
abc_test_abc_sdk/api/__init__.py
abc_test_abc_sdk/api/gifs_api.py
abc_test_abc_sdk/api/stickers_api.py
abc_test_abc_sdk/models/__init__.py
abc_test_abc_sdk/models/get_gifs_by_id200_response.py
abc_test_abc_sdk/models/gif.py
abc_test_abc_sdk/models/gif_images.py
abc_test_abc_sdk/models/gif_images_downsized.py
abc_test_abc_sdk/models/gif_images_downsized_large.py
abc_test_abc_sdk/models/gif_images_downsized_medium.py
abc_test_abc_sdk/models/gif_images_downsized_small.py
abc_test_abc_sdk/models/gif_images_downsized_still.py
abc_test_abc_sdk/models/gif_images_fixed_height.py
abc_test_abc_sdk/models/gif_images_fixed_height_downsampled.py
abc_test_abc_sdk/models/gif_images_fixed_height_small.py
abc_test_abc_sdk/models/gif_images_fixed_height_small_still.py
abc_test_abc_sdk/models/gif_images_fixed_height_still.py
abc_test_abc_sdk/models/gif_images_fixed_width.py
abc_test_abc_sdk/models/gif_images_fixed_width_downsampled.py
abc_test_abc_sdk/models/gif_images_fixed_width_small.py
abc_test_abc_sdk/models/gif_images_fixed_width_small_still.py
abc_test_abc_sdk/models/gif_images_fixed_width_still.py
abc_test_abc_sdk/models/gif_images_looping.py
abc_test_abc_sdk/models/gif_images_original.py
abc_test_abc_sdk/models/gif_images_original_still.py
abc_test_abc_sdk/models/gif_images_preview.py
abc_test_abc_sdk/models/gif_images_preview_gif.py
abc_test_abc_sdk/models/image.py
abc_test_abc_sdk/models/meta.py
abc_test_abc_sdk/models/pagination.py
abc_test_abc_sdk/models/random_gif200_response.py
abc_test_abc_sdk/models/user.py
abc_test_abc_sdk-0.0.1.dist-info/METADATA
abc_test_abc_sdk-0.0.1.dist-info/WHEEL
abc_test_abc_sdk-0.0.1.dist-info/top_level.txt
abc_test_abc_sdk-0.0.1.dist-info/RECORD
